LICENCE.txt
MANIFEST.in
README.rst
setup.py
captains_log/__init__.py
captains_log/test_filler.py
captains_log/backend/__init__.py
captains_log/backend/init.py
captains_log/backend/models.py
captains_log/cli/__init__.py
captains_log/cli/add_entry.py
captains_log/cli/console_script.py
captains_log/cli/devdebug.py
captains_log/cli/entries_history.py
captains_log/cli/installer.py
captains_log/cli/remove_entry.py
captains_log/conf/__init__.py
captains_log/conf/default_settings.py
captains_log/conf/install.py
captains_log/renderer/__init__.py
captains_log/renderer/history.py
python_captains_log.egg-info/PKG-INFO
python_captains_log.egg-info/SOURCES.txt
python_captains_log.egg-info/dependency_links.txt
python_captains_log.egg-info/entry_points.txt
python_captains_log.egg-info/not-zip-safe
python_captains_log.egg-info/requires.txt
python_captains_log.egg-info/top_level.txt