Metadata-Version: 1.1
Name: python-captains-log
Version: 0.6.2
Summary: 
